Database/__init__.py
Database/config.py
Database/exceptions.py
Database/main.py
Database/test.py
Database/text.py
dev_database-0.1.2.dist-info/LICENSE
dev_database-0.1.2.dist-info/METADATA
dev_database-0.1.2.dist-info/WHEEL
dev_database-0.1.2.dist-info/top_level.txt
dev_database-0.1.2.dist-info/RECORD
